spg_pkg/__init__.py
spg_pkg/spg.py
spg_pkg/spg_core.py
spg_pkg/python/__init__.py
spg_pkg/python/sparkplug_b.py
spg_pkg/python/sparkplug_b_pb2.py
spg_pkg-1.0.3.dist-info/LICENSE
spg_pkg-1.0.3.dist-info/METADATA
spg_pkg-1.0.3.dist-info/WHEEL
spg_pkg-1.0.3.dist-info/top_level.txt
spg_pkg-1.0.3.dist-info/RECORD
