Metadata-Version: 2.1
Name: spg-pkg
Version: 1.0.3
Summary: A small example package
Home-page: https://github.com/pypa/sampleproject
Author: sss
Author-email: author@example.com
License: UNKNOWN
Platform: UNKNOWN
Classifier: Programming Language :: Python :: 3
Classifier: License :: OSI Approved :: MIT License
Classifier: Operating System :: OS Independent
Requires-Dist: protobuf
Requires-Dist: paho-mqtt
